jenkinsflow/__init__.py
jenkinsflow/api_base.py
jenkinsflow/checking_state.py
jenkinsflow/flow.py
jenkinsflow/flow_exceptions.py
jenkinsflow/jenkins_api.py
jenkinsflow/jobload.py
jenkinsflow/kill_type.py
jenkinsflow/logging_process.py
jenkinsflow/ordered_enum.py
jenkinsflow/propagation_types.py
jenkinsflow/py.typed
jenkinsflow/rest_api_wrapper.py
jenkinsflow/script_api.py
jenkinsflow/speed.py
jenkinsflow/unbuffered.py
jenkinsflow/cli/__init__.py
jenkinsflow/cli/cli.py
jenkinsflow/cli/jenkinsflow
jenkinsflow/cli/set_build_description.py
jenkinsflow/utils/__init__.py
jenkinsflow/utils/set_build_description.py
jenkinsflow/utils/utils.py
jenkinsflow/visual/flow_vis.html
jenkinsflow/visual/server.py
jenkinsflow/visual/js/__init__.py
jenkinsflow/visual/js/graph.js
jenkinsflow/visual/stylesheets/__init__.py
jenkinsflow/visual/stylesheets/flow.css
jenkinsflow-7.0.6.dist-info/licenses/LICENSE.txt
jenkinsflow-7.0.6.dist-info/METADATA
jenkinsflow-7.0.6.dist-info/WHEEL
jenkinsflow-7.0.6.dist-info/entry_points.txt
jenkinsflow-7.0.6.dist-info/top_level.txt
jenkinsflow-7.0.6.dist-info/zip-safe
jenkinsflow-7.0.6.dist-info/RECORD
