Metadata-Version: 2.4
Name: jenkinsflow
Version: 7.0.6
Summary: Python API with high level build flow constructs (parallel/serial) for Jenkins.
Home-page: https://github.com/lhupfeldt/jenkinsflow.git
Author: Lars Hupfeldt Nielsen
Author-email: lhn@hupfeldtit.dk
License: BSD
Classifier: Development Status :: 5 - Production/Stable
Classifier: Intended Audience :: Developers
Classifier: License :: OSI Approved :: BSD License
Classifier: Natural Language :: English
Classifier: Operating System :: OS Independent
Classifier: Programming Language :: Python :: 3.13
Classifier: Programming Language :: Python :: 3.12
Classifier: Programming Language :: Python :: 3.11
Classifier: Programming Language :: Python :: 3.10
Classifier: Topic :: Software Development :: Libraries
Requires-Python: >=3.10
License-File: LICENSE.txt
Requires-Dist: requests<=3.0,>=2.20
Requires-Dist: atomicfile<=2.0,>=1.0
Requires-Dist: click>=7.0
Requires-Dist: tenjin>=1.1.1
Requires-Dist: psutil>=5.6.6
Requires-Dist: setproctitle>=1.1.10
Requires-Dist: bottle>=0.12.1
Provides-Extra: dev
Requires-Dist: nox; extra == "dev"
Dynamic: license-file
